CLA.md
CODE_OF_CONDUCT.md
CONTRIBUTING.md
MANIFEST.in
README.md
RELEASE_NOTES.md
requirements-test.txt
requirements.txt
setup.cfg
setup.py
meta1api/__init__.py
meta1api/exceptions.py
meta1api/meta1noderpc.py
meta1api/websocket.py
meta1base/__init__.py
meta1base/account.py
meta1base/asset_permissions.py
meta1base/bip38.py
meta1base/chains.py
meta1base/memo.py
meta1base/objects.py
meta1base/objecttypes.py
meta1base/operationids.py
meta1base/operations.py
meta1base/signedtransactions.py
meta1base/transactions.py
meta1testnet/__init__.py
meta1testnet/account.py
meta1testnet/amount.py
meta1testnet/asset.py
meta1testnet/block.py
meta1testnet/blockchain.py
meta1testnet/blockchainobject.py
meta1testnet/committee.py
meta1testnet/dex.py
meta1testnet/exceptions.py
meta1testnet/genesisbalance.py
meta1testnet/htlc.py
meta1testnet/instance.py
meta1testnet/market.py
meta1testnet/memo.py
meta1testnet/message.py
meta1testnet/meta1.py
meta1testnet/notify.py
meta1testnet/price.py
meta1testnet/proposal.py
meta1testnet/storage.py
meta1testnet/transactionbuilder.py
meta1testnet/utils.py
meta1testnet/vesting.py
meta1testnet/wallet.py
meta1testnet/witness.py
meta1testnet/worker.py
meta1testnet.egg-info/PKG-INFO
meta1testnet.egg-info/SOURCES.txt
meta1testnet.egg-info/dependency_links.txt
meta1testnet.egg-info/requires.txt
meta1testnet.egg-info/top_level.txt