Metadata-Version: 1.2
Name: meta1testnet
Version: 0.2.5
Summary: Python library for meta1testnet
Home-page: https://github.com/meta1-blockchain/meta1-python-testnet
Author: Rostislav Gogolauri
Author-email: invest@lampgram.com
Maintainer: Rostislav Gogolauri
Maintainer-email: invest@lampgram.com
License: UNKNOWN
Download-URL: https://github.com/meta1-blockchain/meta1-python-testnet/tarball/0.2.5
Keywords: meta1testnet,library,api,rpc
Platform: UNKNOWN
Classifier: License :: OSI Approved :: MIT License
Classifier: Operating System :: OS Independent
Classifier: Programming Language :: Python :: 3
Classifier: Development Status :: 3 - Alpha
Classifier: Intended Audience :: Developers
Classifier: Intended Audience :: Financial and Insurance Industry
Classifier: Topic :: Office/Business :: Financial
